[
    {
        "公司名稱": "雋析科技股份有限公司/-",
        "成立時間": "2022",
        "統一編號": "90223740",
        "公司狀態": "核准設立",
        "團隊人數": "1",
        "實收資本額(元/新台幣)": "10,000,000",
        "負責人": "劉榮宗",
        "主分類": "Hardware",
        "官方網站": "Not Provided",
        "專利狀況": "公告專利總數︰0；發明專利︰0；新型專利︰0；設計專利︰0",
        "產品/服務簡介": "客製化雷達演算架構設計服務、先進雷達次系統開發服務",
        "公司簡介": "雋析科技是一家專注於先進雷達技術研發的公司，致力於開發AI智慧化雷達系統，並將技術落實於毫米波商用雷達和特定專用雷達等產品。我們專注於智慧照護應用，提供客戶所需之雷達軟硬體智財授權以及雷達次系統產品。雋析科技的專業團隊能夠根據客戶需求，提供客製化的解決方案，並在產品開發、部署和維護的各個階段支援客戶。我們的研發團隊不斷探索新的技術和方法，以確保產品和服務始終處於行業的領先地位。雋析科技的目標是成為全球AI智慧化雷達技術的領導者，為客戶提供卓越的解決方案。",
        "公司註冊地址": "新竹縣竹北市中興里復興三路二段168號9樓之5"
    }
]