[
    {
        "公司名稱": "愛膜力事業有限公司/-",
        "成立時間": "2021",
        "統一編號": "90419998",
        "公司狀態": "核准設立",
        "團隊人數": "未揭露",
        "實收資本額(元/新台幣)": "0",
        "負責人": "王幸娟",
        "主分類": "SalesandMarketing",
        "官方網站": "https://www.imore.tw/",
        "專利狀況": "公告專利總數︰0；發明專利︰0；新型專利︰0；設計專利︰0",
        "產品/服務簡介": "封口膜及通路商的數位媒合系統服務商",
        "公司簡介": "飲料封口膜廣告一站式服務愛膜力主要從事封口膜及通路商的數位媒合系統服務商，建構封口膜廣告服務模式，在既有飲料封口膜上賦予品牌廣告曝光的功能，以新商業創新服務為主軸。以封口包裝創新數位媒合平台為媒介，針對廣告主、商家、消費者所需的每個階段創造價值。打造O2O線上線下虛實整合，形成封口膜廣告一站式服務。",
        "公司註冊地址": "臺中市中區民族路23號3樓之2"
    }
]