[
    {
        "公司名稱": "佳真國際企業有限公司/JIAZHENINTERNATIONALENTERPRISECORP.",
        "成立時間": "2015",
        "統一編號": "24953962",
        "公司狀態": "核准設立",
        "團隊人數": "未揭露",
        "實收資本額(元/新台幣)": "0",
        "負責人": "沈佳泰",
        "主分類": "Hardware",
        "官方網站": "https://www.jz-touchsignage.com/",
        "專利狀況": "公告專利總數︰0；發明專利︰0；新型專利︰0；設計專利︰0",
        "產品/服務簡介": "互動電子白板；數位看板；多媒體取叫號系統；拼接電視牆；KIOSK；AIOT物聯網應用",
        "公司簡介": "佳真國際企業團隊，長期與不同行業別的客戶合作於環保無紙化之數位看板市場及KIOSK觸控導覽系統，並奉行「服務客戶，貢獻社會」之想法﹐致力於電梯業、銀行、娛樂、教育藝文、政府機關、交通運輸、觀光飯店、餐飲、製造業廠房、醫療院所等…。佳真持續將電子看板,數位看板,AIoT應用,RWD設計,KIOSK觸控應用結合於智慧醫療,智慧教室和智慧建築中！並在眾多領域中提供創新整合的解決方案，同時以卓越客製化開發能力，滿足不同客戶的需求、持續協助客戶創造利潤，並與客戶攜手成長於AIoT（人工智慧物聯網）。",
        "公司註冊地址": "臺北市中正區中山北路1段2號4樓之2"
    }
]