[
    {
        "公司名稱": "瑞德機械工業股份有限公司/-",
        "成立時間": "2017",
        "統一編號": "61762326",
        "公司狀態": "核准設立",
        "團隊人數": "未揭露",
        "實收資本額(元/新台幣)": "150,750,000",
        "負責人": "秦宏銘",
        "主分類": "Manufacturing",
        "官方網站": "Not Provided",
        "專利狀況": "公告專利總數︰0；發明專利︰0；新型專利︰0；設計專利︰0",
        "產品/服務簡介": "專業電動車（E-BIKE）外銷製造廠，及自有品牌XRiDER、士萊德等",
        "公司簡介": "E-BIKE代工生產及ODM開發為主，於2018年投入歐洲市場，OEM品牌遍及歐洲、美國各大廠。並具自有品牌XRiDER、士萊德等。",
        "公司註冊地址": "臺中市后里區墩南里舊社路5之9號"
    }
]