[
    {
        "公司名稱": "晧揚環境科技股份有限公司/HAO-YANGENVIRONMENTSCIENCELTD.",
        "成立時間": "2014",
        "統一編號": "24748457",
        "公司狀態": "核准設立",
        "團隊人數": "未揭露",
        "實收資本額(元/新台幣)": "40,000,000",
        "負責人": "楊琛",
        "主分類": "Sustainability",
        "官方網站": "http://www.itrash.com.tw/front/bin/home.phtml#",
        "專利狀況": "公告專利總數︰2；發明專利︰2；新型專利︰0；設計專利︰0",
        "產品/服務簡介": "iTrashSmartCity智慧城市垃圾回收整合系統。這套垃圾回收整合系統，不僅24小時提供服務，民眾只要刷悠遊卡或一卡通，就可立即秤重計費，甚至回收8個鐵鋁罐就可獲得1元加值回饋金，還可累計。",
        "公司簡介": "皓揚環境科技股份有限公司結合智能科技與物聯網技術，改變既有的垃圾處理模式，「要的不只是方便，而是落實垃圾減量、資源回收，讓環境變得更好。」，以重量計費的方式，應用至少六項專利技術，結合智能控制系統，iTrash於焉誕生。我們得到經濟部與台北市SBIR計畫協助，以及國發基金的補助，讓我們獲得美國、歐盟等16個技術專利。",
        "公司註冊地址": "桃園市桃園區藝文一街86之1號17樓"
    }
]