[
    {
        "公司名稱": "聯聚電子股份有限公司/PartilinkInc.",
        "成立時間": "2018",
        "統一編號": "50860356",
        "公司狀態": "核准設立",
        "團隊人數": "未揭露",
        "實收資本額(元/新台幣)": "98,651,088",
        "負責人": "彭仁熠",
        "主分類": "Hardware",
        "官方網站": "https://www.partilink.com.tw/tw/index.php",
        "專利狀況": "公告專利總數︰1；發明專利︰1；新型專利︰0；設計專利︰0",
        "產品/服務簡介": "影音多媒體的傳輸、轉換、儲存",
        "公司簡介": "Partilink聯聚電子專注於創新研發影音多媒體的傳輸、轉換、儲存等產品.產品主要應用在影像訊號的增強與延長傳輸距離、各種影音訊號的格式轉換，或是影音訊號切換等等...。聯聚科技總部位於台灣台北市,於中國大陸深圳市設有分公司。訴求高品質、穩定可靠的產品是聚聯科技的堅持和文化；公司的成員皆為相關領域的資深人員,除了不斷開發最新科技的新產品,也可以針對客戶的需求提供極具彈性與及時性的產品客製化服務。",
        "公司註冊地址": "臺北市內湖區行善路48巷18號2樓之2"
    }
]