[
    {
        "公司名稱": "觸覺科技有限公司/-",
        "成立時間": "2022",
        "統一編號": "90250984",
        "公司狀態": "核准設立",
        "團隊人數": "未揭露",
        "實收資本額(元/新台幣)": "0",
        "負責人": "楊豐憶",
        "主分類": "HealthCare",
        "官方網站": "https://www.mobbytw.com/",
        "專利狀況": "公告專利總數︰0；發明專利︰0；新型專利︰0；設計專利︰0",
        "產品/服務簡介": "輔具創新研發、觸覺引導地圖、觸覺教材設計平台、觸覺感官教材、保齡球語音引導系統",
        "公司簡介": "觸覺科技有限公司專注於提升觸覺體驗和無障礙設計，開發了多種科技應用以幫助視障人士。公司利用3D列印和熱成形技術，製作觸圖以便視障者感知物體形狀，促進互動學習。憑藉其創新技術和商業模式，多次獲得產業獎項，顯示出其在市場上的競爭力。MobbyInc.成立於2020年，由楊豐憶（現任執行長）攜手國際夥伴於台灣創立;品牌成立初期攜手多元族群參與產品設計與社會倡議，秉持著以人為本、科技創新與通用設計的理念提供產品服務。",
        "公司註冊地址": "臺南市永康區中華路144-1號地下一層"
    }
]