[
    {
        "公司名稱": "台和工程顧問股份有限公司/-",
        "成立時間": "2017",
        "統一編號": "59307575",
        "公司狀態": "核准設立",
        "團隊人數": "未揭露",
        "實收資本額(元/新台幣)": "16,000,000",
        "負責人": "張玉秀",
        "主分類": "Sustainability",
        "官方網站": "https://www.taihe.com.tw/home.htm",
        "專利狀況": "公告專利總數︰0；發明專利︰0；新型專利︰0；設計專利︰0",
        "產品/服務簡介": "業務工作包括環保相關、分生技術顧問、環保處理系統改善設計規劃、土壤地下水調查評估/整治、環保文件之撰寫及簽證、監督處理工程之進行、處理功能測試及排放許可申請、申報、透地雷達檢測，及協助業者辦理相關環保事務等，透過認真負責的工作態度及專業知識，提供完善之技術服務。",
        "公司簡介": "台和工程顧問股份有限公司願景是成為一家值得信賴的工程顧問公司，並致力於改善環境。管理方式強調扁平化，讓同仁除工作學習外仍保有自我發展空間，組織團隊強調融合及創新，定期教育訓練強化組織學習及心得分享。成員主要攬自國內外大專院校環工、生物、化工、地質等相關工程、生態、分子生物系所背景之專業人才，本公司之業務工作包括環保、分生技術顧問、環保處理系統改善設計規劃、土壤地下水調查/整治、環保文件之撰寫及簽證、監督處理工程之進行、處理功能測試及排放許可申請、申報，協助業者辦理相關環保事務等，透過認真負責的工作態度及專業知識，提供完善之技術服務。",
        "公司註冊地址": "高雄市前鎮區復興四路12號5樓之20"
    }
]