[
    {
        "公司名稱": "昊偉環境科技股份有限公司/HaoWeiEnvironmentalTechnologyCo.,Ltd.",
        "成立時間": "2020",
        "統一編號": "83759535",
        "公司狀態": "核准設立",
        "團隊人數": "5",
        "實收資本額(元/新台幣)": "6,000,000",
        "負責人": "賀朝建",
        "主分類": "Energy",
        "官方網站": "https://hw-et.com/",
        "專利狀況": "公告專利總數︰0；發明專利︰0；新型專利︰0；設計專利︰0",
        "產品/服務簡介": "貝斯特系列汽柴油添加劑、ECO系列環保處理器",
        "公司簡介": "昊偉環境科技股份有限公司成立於2020年，是一家專門於奈米材料、汽柴油添加劑、節能環保設備以及環保新能源的公司。目前主要產品為貝斯特系列汽柴油添加劑、ECO系列環保處理器。",
        "公司註冊地址": "臺北市中正區忠孝西路1段41號13樓之12"
    }
]