[
    {
        "公司名稱": "極山股份有限公司/noviumtaiwanInc.",
        "成立時間": "2019",
        "統一編號": "83449820",
        "公司狀態": "核准設立",
        "團隊人數": "12",
        "實收資本額(元/新台幣)": "6,315,790",
        "負責人": "梁國鴻",
        "主分類": "ConsumerGoods",
        "官方網站": "https://www.novium.tw",
        "專利狀況": "公告專利總數︰2；發明專利︰1；新型專利︰1；設計專利︰0",
        "產品/服務簡介": "HOVERPEN自立筆",
        "公司簡介": "novium致力於研發創造市場上未出現過的新奇產品，「自立筆系列」，為世界第一組無電漂浮筆。這樣全新概念的漂浮筆座組，重新定義人與筆的關係，擁有多國專利，出貨到全球70個國家，營收100%來自自有品牌產品，外銷連續三年佔比七成以上，遠至南非、太平洋的小島都看的到自立筆的身影。2019至今，銷售出的自立筆可以疊成18座101、超過聖母峰的高度。因為產品十足的創新與獨特性，海外銷售擁有12國經銷代理，並持續深入國際拓銷中，目標成為國際DTC品牌。",
        "公司註冊地址": "臺北市信義區松德路161號15樓"
    }
]