[
    {
        "公司名稱": "華文創股份有限公司/MandarinVisionCo.,Ltd",
        "成立時間": "2012",
        "統一編號": "53935556",
        "公司狀態": "核准設立",
        "團隊人數": "未揭露",
        "實收資本額(元/新台幣)": "60,000,000",
        "負責人": "何琇瓊",
        "主分類": "MediaandEntertainment",
        "官方網站": "https://www.mandarinvision.com/",
        "專利狀況": "公告專利總數︰0；發明專利︰0；新型專利︰0；設計專利︰0",
        "產品/服務簡介": "影視專案開發與製作、國內外電影發行、媒體經營與新媒體運營等",
        "公司簡介": "成立於2012年，業務範圍涵蓋影視專案開發與製作、國內外電影發行、媒體經營與新媒體運營等項目。2015年5月，邀請資深電影監製葉如芬女士加入，帶領團隊，業務主力為電影開發、投資與製作、海外發行，及優質電視影集與新媒體內容的開拓，致力於打造華文世界導演、製片及投資者的完善平台。期許能整合文創產業的強項資源，以華文電影創作者為基礎，連結亞洲與世界，製作出更多好看動人的影視作品。2016年3月，華文創正式邀請資深電視人何琇瓊女士擔任董事長，持續以建構全球華文影視傳播市場的資源整合體系為首要目標，結合「資本」、「娛樂」、「傳媒」三大文創產業關鍵元素，運用專業化、系統化的操作模式，全力發展為大中華區專業的影視集團。",
        "公司註冊地址": "臺北市大安區復興南路2段283號9樓"
    }
]