[
    {
        "公司名稱": "京鎧電波股份有限公司/POSEIDONMICROWAVECORPORATION",
        "成立時間": "2014",
        "統一編號": "54637008",
        "公司狀態": "核准設立",
        "團隊人數": "未揭露",
        "實收資本額(元/新台幣)": "12,500,000",
        "負責人": "李仲桓",
        "主分類": "Hardware",
        "官方網站": "Not Provided",
        "專利狀況": "公告專利總數︰0；發明專利︰0；新型專利︰0；設計專利︰0",
        "產品/服務簡介": "新式電磁場探頭、電磁場量測系統",
        "公司簡介": "以自有的創新近場量測技術開發快速準確、可大量使用但相對低價的電磁量測設備，減少研發工程師的量測負擔及加速產品的開發時程，同時在產線協助品質控管。",
        "公司註冊地址": "新竹市東區新安路5號4樓之1(R501-1)室"
    }
]