[
    {
        "公司名稱": "和四時生化科技股份有限公司/PakkuNutritionCo.,Ltd",
        "成立時間": "2021",
        "統一編號": "91057071",
        "公司狀態": "核准設立",
        "團隊人數": "7",
        "實收資本額(元/新台幣)": "1,600,000",
        "負責人": "王楓喬",
        "主分類": "HealthCare",
        "官方網站": "https://www.pakku.com.tw/",
        "專利狀況": "公告專利總數︰1；發明專利︰0；新型專利︰1；設計專利︰0",
        "產品/服務簡介": "客製化保健品",
        "公司簡介": "我們是pakku®，我們的母公司愛騛生技，過去十年來專注於天然植物原料應用研究與供應，為世界知名藥廠原料供應商，嚴格把關品質受到肯定。第一個十年，我們專注於成為台灣植物原料的專家；第二個十年，我們希望把前十年的成果與經驗，以產品的形式，通過AI問卷系統，分享給你！pakku®的誕生就是想藉由你的內在需求「真實」告訴你的身體所需。利用中國農業大學等單位聯合研究之內容，利用AI數據挖掘近20萬份數據，沒有昂貴的諮詢費用，我們的免費「客製化」AI問卷系統同樣能為您量身推薦適合的營養保健品，也因為省去這昂貴的諮詢費用，我們回饋到消費者身上讓您知道健康的取得並非與龐大花費畫上等號！拿掉過度包裝、華麗行銷，我們希望扮演的是「最懂你」的照顧者。現在開始，褪下你日常的武裝，告訴我們你內心與身體的需要吧！",
        "公司註冊地址": "臺北市大安區復興南路2段157號3樓之2"
    }
]