[
    {
        "公司名稱": "亞瑞特數位社群行銷有限公司/-",
        "成立時間": "2016",
        "統一編號": "43904816",
        "公司狀態": "核准設立",
        "團隊人數": "36",
        "實收資本額(元/新台幣)": "0",
        "負責人": "黃逸旻",
        "主分類": "SalesandMarketing",
        "官方網站": "https://www.aretedigitalsocial.com/%E5%89%AF%E6%9C%AC-%E7%B2%BE%E5%BD%A9%E4%BD%9C%E5%93%81-%E7%A4%BE%E7%BE%A4%E7%B6%93%E7%87%9F%E9%A0%81?gad_source=1&gclid=Cj0KCQjw0Oq2BhCCARIsAA5hubXn8zEd0oOboJPtXhVQwsKsQsYd4UvN8VGsCbgJZy-xBchXzP3d8rcaAn51EALw_wcB",
        "專利狀況": "公告專利總數︰0；發明專利︰0；新型專利︰0；設計專利︰0",
        "產品/服務簡介": "1.數位行銷傳播；2.社群自媒體管理；3.數位媒體宣傳；4.兩岸跨境行銷；5.網路公關；6.品牌電商導購；7.數位社群課程；8.全球社群行銷；9.內容行銷；10.網路輿情解析",
        "公司簡介": "數位社群行銷一站式服務，環繞消費者接觸點與共鳴點，打造行銷傳播的生態系統，貫穿平台策略與內容創意！基於大數據、社群傾聽、監控優化，挖掘了解消費者洞察。專業證照認證養成，內部數位社群顧問人材！",
        "公司註冊地址": "臺北市松山區東興路28號11樓"
    }
]