[
    {
        "公司名稱": "欣鉅興科技股份有限公司/-",
        "成立時間": "2021",
        "統一編號": "83201799",
        "公司狀態": "核准設立",
        "團隊人數": "未揭露",
        "實收資本額(元/新台幣)": "572,274,970",
        "負責人": "顏立盛",
        "主分類": "Hardware",
        "官方網站": "http://uniconntech.com.tw/",
        "專利狀況": "公告專利總數︰0；發明專利︰0；新型專利︰0；設計專利︰0",
        "產品/服務簡介": "主要產品為測試介面專用之電路板，服務的產業包括半導體、航太(航天)、汽車、電子零組件…等。",
        "公司簡介": "欣鉅興科技股份有限公司創立於2021年1月，以客戶至上的核心經營理念、不斷開發最新科技及尖端製造技術，提供客戶最佳產品及服務，產品跨越多領域產業，主要產品為半導體IC測試專用載板，服務的產業包括半導體、航太(航天)、汽車、電子零組件…等。欣鉅興科技以提升客戶競爭力為主要目標，在技術上不斷研發創新，提供客戶最佳的解決方案，以創造客戶價值為我們的職志。",
        "公司註冊地址": "新北市三峽區介壽路1段412巷19號"
    }
]