[
    {
        "公司名稱": "松赫生物科技股份有限公司/-",
        "成立時間": "2021",
        "統一編號": "91083063",
        "公司狀態": "解散",
        "團隊人數": "未揭露",
        "實收資本額(元/新台幣)": "5,000,000",
        "負責人": "-",
        "主分類": "Biotechnology",
        "官方網站": "Not Provided",
        "專利狀況": "公告專利總數︰0；發明專利︰0；新型專利︰0；設計專利︰0",
        "產品/服務簡介": "產品著重於友善環境，以愛護地球的理念出發，研發推廣安全、無抗藥性產品！目前已市場規劃分為：HomeCare、PersonalCare、PetCare、PublicCare，主要是將外用益生菌應用至生活中！以好菌抵制壞菌，創造低敏健康環境，這也就是我們為什麼致力於台灣自主研發與推廣友善、將天然的好菌產品推廣到全世界！",
        "公司簡介": "松赫是一家2021年新成立的生技公司，產品著重於友善環境，以愛護地球的理念出發，研發推廣安全、無抗藥性產品！目前已市場規劃分為：HomeCare、PersonalCare、PetCare、PublicCare，主要是將外用益生菌應用至生活中！以好菌抵制壞菌，創造低敏健康環境！",
        "公司註冊地址": "新北市樹林區中洲街31號(1樓)"
    }
]