[
    {
        "公司名稱": "時空軸興業有限公司/ELEMATRIXLTD.CO.",
        "成立時間": "2016",
        "統一編號": "60223510",
        "公司狀態": "核准設立",
        "團隊人數": "未揭露",
        "實收資本額(元/新台幣)": "0",
        "負責人": "賴正雄",
        "主分類": "ConsumerGoods",
        "官方網站": "https://www.whaledon.com/",
        "專利狀況": "公告專利總數︰0；發明專利︰0；新型專利︰0；設計專利︰0",
        "產品/服務簡介": "後背包",
        "公司簡介": "\"WhaleDon鯨讚，發跡於台灣的新銳團隊，創辦人Steve&Terry秉持著『解決生活周遭的基本元件中最根本的問題』理念並勇往直前。WhaleDon靈感取自於英文WellDone意指「做得好！」，延伸出以大海中獨立勇敢的Whale「鯨魚」作為品牌意象。『不屈不撓堅持追求極致的好，如鯨魚（Whale）般往地球未知的盡頭前進！』「生活中總是會遇上一些想克服的問題。」我們會先從一個核心問題出發，希望能以「1+1>2」的理念去大膽實驗各種材料和技術。當然途中也發現各領域中都擁有獨到的技術和產品，大多侷限使用在單一產業產品中，更堅定了WhaleDon要為這世界靈巧和貼心的發明開拓一條全新道路！",
        "公司註冊地址": "臺中市太平區聖和里長龍路一段166巷38號4樓"
    }
]