[
    {
        "公司名稱": "耕山農創股份有限公司/-",
        "成立時間": "2014",
        "統一編號": "24642052",
        "公司狀態": "核准設立",
        "團隊人數": "未揭露",
        "實收資本額(元/新台幣)": "150,000",
        "負責人": "邱星崴",
        "主分類": "TravelandTourism",
        "官方網站": "https://www.facebook.com/mountainlodge2014/",
        "專利狀況": "公告專利總數︰0；發明專利︰0；新型專利︰0；設計專利︰0",
        "產品/服務簡介": "老寮Hostel，透過深度旅遊及背包住宿提供服務和體驗，帶領人們深入了解農村。開設Valai農創店，提供餐飲、特色農產與深度旅遊的農創服務，為外界了解農村的方式提供了另一項新選擇。",
        "公司簡介": "為了重新打造在地的產業鏈、活化故鄉的山水，創辦人邱星崴經過長期的調查與研究後，成立了「耕山農創」並以「把山種回來」作為經營使命，期望打造外界認識苗栗南庄山林的入口，讓人們透過旅行「一不小心」便愛上這塊土地。",
        "公司註冊地址": "苗栗縣南庄鄉南江村22鄰南江街50號"
    }
]