[
    {
        "公司名稱": "陽昇應用材料股份有限公司/CHEERINGSUNAPPLIEDMATERIALSCO.,LTD.",
        "成立時間": "2012",
        "統一編號": "53811056",
        "公司狀態": "核准設立",
        "團隊人數": "未揭露",
        "實收資本額(元/新台幣)": "74,600,000",
        "負責人": "莊弘毅",
        "主分類": "Manufacturing",
        "官方網站": "http://www.cheeringsun.com.tw/",
        "專利狀況": "公告專利總數︰5；發明專利︰4；新型專利︰1；設計專利︰0",
        "產品/服務簡介": "-",
        "公司簡介": "陽昇應用材料股份有限公司主要的核心技術有兩個領域。1.陶瓷載板：利用自主研發之陶瓷加工技術及厚膜印刷燒結技術，可製造出各種用途之陶瓷載板。特別是有3D結構(雙面導通孔，立體圍繞壁...等等）之設計，可應用為LED,IC封裝載板，或電路保護元件之基板等用途。2.磁性材料之成型：應用自主研發之一體成型技術，製作微型功率電感(powerchoke)所須之磁芯，可依不同領域之須求，提供不同磁性材料系統。使功率電感之設計及製作更具多樣性。",
        "公司註冊地址": "桃園市大園區中山南路二段156號"
    }
]