[
    {
        "公司名稱": "豐誠秀極有限公司/ToyotomiHideyoshiCo.,Ltd.",
        "成立時間": "2019",
        "統一編號": "84009477",
        "公司狀態": "廢止",
        "團隊人數": "未揭露",
        "實收資本額(元/新台幣)": "0",
        "負責人": "-",
        "主分類": "ConsumerGoods",
        "官方網站": "https://www.facebook.com/tomioshi/",
        "專利狀況": "公告專利總數︰0；發明專利︰0；新型專利︰0；設計專利︰0",
        "產品/服務簡介": "智能電子香買賣/租借",
        "公司簡介": "智能電子香買賣/租借以電代火、以水煙取代香煙，就台灣及世界各地燃香拜拜文化為發想，融合擴香機、MP3、IoT，點出華人傳統文化印象結合科技應用的創新表現。宗教科技文創網路商城以宗教文化為主軸，結合宗教科技文創，發展一系列商品，加上台灣既有之供品文化，結合相關宗教節慶行事曆，打造台灣特有的宗教科技文創網路商城。",
        "公司註冊地址": "臺北市松山區復興北路201號4樓之2"
    }
]