[
    {
        "公司名稱": "豐譽永續科技股份有限公司/FENGYUSUSTAINABLETECHNOLOGYCO.,LTD.",
        "成立時間": "2014",
        "統一編號": "24574857",
        "公司狀態": "核准設立",
        "團隊人數": "6",
        "實收資本額(元/新台幣)": "20,000,000",
        "負責人": "謝佶燁",
        "主分類": "RealEstate",
        "官方網站": "https://www.fengyu.com.tw/sustainable",
        "專利狀況": "公告專利總數︰5；發明專利︰2；新型專利︰3；設計專利︰0",
        "產品/服務簡介": "微奈米氣泡發展及應用",
        "公司簡介": "以創新研發,提共食品安全,環境保護,善盡社會責任,為本公司選擇在好山好水宜蘭設立的宗旨。微奈米氣泡發展及應用可應用於九大領域，如：農業種植、漁業養殖、工業設備清洗、污水淨化、商旅生活、醫療照護、畜牧防疫、飲用水淨化及食材清洗。其市場商機及潛力無窮。本公司核心技術的開發已完成,系統可應用在食安.醫美.水汙及空汙市場等,現設備已導入國內大型連鎖餐廳及上市公司化工應用設備",
        "公司註冊地址": "宜蘭縣宜蘭市宜科南路15號5樓之18"
    }
]