[
    {
        "公司名稱": "采億科技股份有限公司/TSAIYITECHNOLOGYINC.",
        "成立時間": "2013",
        "統一編號": "54317194",
        "公司狀態": "核准設立",
        "團隊人數": "45",
        "實收資本額(元/新台幣)": "6,000,000",
        "負責人": "許峰誌",
        "主分類": "Advertising",
        "官方網站": "https://www.tsaiyitech.com/",
        "專利狀況": "公告專利總數︰1；發明專利︰0；新型專利︰1；設計專利︰0",
        "產品/服務簡介": "廣告投放、社群經營",
        "公司簡介": "研發社群互動模組,使品牌在社群互動上更為有趣。廣告投放服務、社群經營服務強化品牌推廣。結合線上與線下推廣，提供創意、策略、媒體服務。合作過的品牌如金車、伯朗咖啡館、博士倫、3M、寶礦力水得、可樂娜啤酒、OK超商、UNIQLO、碧歐斯、亞尼克等多家知名企業。",
        "公司註冊地址": "新北市三重區重新路5段609巷20號6樓之4"
    }
]