[
    {
        "公司名稱": "宏康智慧股份有限公司/-",
        "成立時間": "2014",
        "統一編號": "54679772",
        "公司狀態": "核准設立",
        "團隊人數": "未揭露",
        "實收資本額(元/新台幣)": "5,000,000",
        "負責人": "章正國",
        "主分類": "InformationTechnology",
        "官方網站": "https://www.hcinnovation.tw/",
        "專利狀況": "公告專利總數︰1；發明專利︰0；新型專利︰1；設計專利︰0",
        "產品/服務簡介": "感監測設備、軟體介面、數據分析",
        "公司簡介": "宏康智慧(HonConnInnovation,HCI)主要專精於資訊系統軟體開發，並著重創新科技服務。專業領域包括電信營運及帳務系統(BSS)、串流影音平台(OTT)BSS、企業資源規劃(ERP)、物聯網(IOT)、節能減排(EMS)、數位服務、商業智慧(BI)、線上支付、電子商務、智慧商業(O2O)、APP應用設計、視覺設計(UI&UX)等開發、建置和整合應用。HCI除了具有豐富的專案系統開發建置服務經驗外，亦研發自有產品平台，技術可完全掌控，可依客戶需求進行設計和研發，並能依照市場反應或是使用者反饋，立即做出修正和優化。",
        "公司註冊地址": "臺北市中山區南京東路1段34號7樓"
    }
]