[
    {
        "公司名稱": "孫悟空創意發明股份有限公司/-",
        "成立時間": "2015",
        "統一編號": "42670348",
        "公司狀態": "核准設立",
        "團隊人數": "未揭露",
        "實收資本額(元/新台幣)": "49,000,000",
        "負責人": "鄧鴻吉",
        "主分類": "FinancialServices",
        "官方網站": "http://crowdfunding.itweald.com/funding/",
        "專利狀況": "公告專利總數︰1；發明專利︰0；新型專利︰0；設計專利︰1",
        "產品/服務簡介": "專利發明產品商品化、量產",
        "公司簡介": "「孫悟空創意發明募資平台」是幫助「創意發明者」將發明品具體呈現，直接在網站上對外公開陳述，向群眾募集少量商品化的必要資金，讓創意發明的點子得以商品化，除回饋給募資者（即回饋型集資、預購型集資），也讓商品可以在市場上有曝光與測試的機會。",
        "公司註冊地址": "臺中市西區公益里公益路223號地下一樓"
    }
]