[
    {
        "公司名稱": "台基盟生技股份有限公司/TaiwanGenomeIndustryAllianceInc.",
        "成立時間": "2017",
        "統一編號": "52608581",
        "公司狀態": "核准設立",
        "團隊人數": "未揭露",
        "實收資本額(元/新台幣)": "258,506,380",
        "負責人": "陳振忠",
        "主分類": "ScienceandEngineering",
        "官方網站": "https://www.tgiainc.com/",
        "專利狀況": "公告專利總數︰0；發明專利︰0；新型專利︰0；設計專利︰0",
        "產品/服務簡介": "基因檢測",
        "公司簡介": "台基盟公司之成立，係響應國家衛生研究院「亞太生醫矽谷精準醫療旗艦計畫」，提供高品質生醫產品與服務，以精準醫療(PrecisionMedicine)改善人類健康之任務，由多家公司在國衛院輔導下共同創立，發展多項核心能力並開拓其商業潛力，諸如基因體、動物科學、基因檢測產品開發、製造及服務。台基盟公司已於106年與國家衛生研究院簽訂「精準醫療平台技術開發及產業應用」產學合作案，合作範範包含次世代基因體定序(NextGenerationSequencing,NGS)服務及應用、癌症動物模式之開發應",
        "公司註冊地址": "新竹縣竹北市生醫五路66號8樓之6"
    }
]