[
    {
        "公司名稱": "好滴科技股份有限公司/-",
        "成立時間": "2021",
        "統一編號": "90897061",
        "公司狀態": "解散已清算完結",
        "團隊人數": "未揭露",
        "實收資本額(元/新台幣)": "0",
        "負責人": "-",
        "主分類": "CommerceandShopping",
        "官方網站": "Not Provided",
        "專利狀況": "公告專利總數︰0；發明專利︰0；新型專利︰0；設計專利︰0",
        "產品/服務簡介": "推薦聚餐優惠的美食平台",
        "公司簡介": "好滴科技是一家推薦聚餐優惠的美食平台，我們堅持「只提供聚餐體驗最好的餐廳」，透過AI演算法提供附近地區最佳的聚餐優惠選擇，為優秀的餐飲業者與聚餐愛好者搭起友善的橋樑。以商業平台為根基，發掘不同國家具有獨特價值的品牌，推入為世界性品牌。",
        "公司註冊地址": "-"
    }
]