[
    {
        "公司名稱": "義澤科技有限公司/-",
        "成立時間": "2019",
        "統一編號": "82869112",
        "公司狀態": "核准設立",
        "團隊人數": "3",
        "實收資本額(元/新台幣)": "0",
        "負責人": "楊仁賓",
        "主分類": "InformationTechnology",
        "官方網站": "https://ezertech.com.tw/",
        "專利狀況": "公告專利總數︰3；發明專利︰0；新型專利︰3；設計專利︰0",
        "產品/服務簡介": "人工智慧解決方案、雲端數據資料分析",
        "公司簡介": "數位技術的時代來臨，義澤科技協助客戶在數位轉型的​過程中，感受到數位化帶來的便利與輕鬆，並能改善製​造流程，提升效率。義澤為客戶設計專屬的智慧製造解決方案，協助客戶在​既有的流程中導入自動化及智慧化，實際導入於金屬加​工、食品包裝、化工製造等不同的行業別，致力成為各​行各業數位轉型的好夥伴。",
        "公司註冊地址": "高雄市鼓山區美術南二路70巷37號2樓"
    }
]