[
    {
        "公司名稱": "毫安時股份有限公司/mAhIncorporation",
        "成立時間": "2018",
        "統一編號": "42991952",
        "公司狀態": "解散",
        "團隊人數": "未揭露",
        "實收資本額(元/新台幣)": "10,000,000",
        "負責人": "-",
        "主分類": "ConsumerGoods",
        "官方網站": "Not Provided",
        "專利狀況": "公告專利總數︰0；發明專利︰0；新型專利︰0；設計專利︰0",
        "產品/服務簡介": "-",
        "公司簡介": "毫安時股份有限公司，致力於打造顧客更好的配戴體驗，透過新興科技與傳統工藝的結合，我們希望能解決每個人配戴眼鏡的不適及困擾，為眼鏡產業帶來創新與突破。如何替顧客量身打造一副好的眼鏡，並提供每位受眼鏡困擾者更好的配戴體驗，是我司一直以來致力的目標。透過科技化的精密分析，人性化的溫暖服務，做出完美眼鏡，是我們對顧客的堅持與承諾。",
        "公司註冊地址": "臺北市內湖區金莊路100號10樓之8"
    }
]