[
    {
        "公司名稱": "真克拉生物科技股份有限公司/TRULYCOLYCO,.LTD",
        "成立時間": "2018",
        "統一編號": "82778133",
        "公司狀態": "解散",
        "團隊人數": "未揭露",
        "實收資本額(元/新台幣)": "100,000",
        "負責人": "-",
        "主分類": "AgricultureandFarming",
        "官方網站": "Not Provided",
        "專利狀況": "公告專利總數︰0；發明專利︰0；新型專利︰0；設計專利︰0",
        "產品/服務簡介": "飼料添加劑產品",
        "公司簡介": "公司理念為環保，健康、自然。目前主產品為保健型之飼料添加劑-大腸桿菌素，其功能不僅健康且更包含環境保護概念，也就是強調其增肉率、飼料換肉率等，其功效優於市場上各種主要的飼料添加劑產品，包括益生菌、酵素等，同時又可取代及減少抗生素的使用，符合國際市場家畜及家禽市場全面禁用抗生素的趨勢。",
        "公司註冊地址": "臺中市南區興大路46號13樓之1"
    }
]