[
    {
        "公司名稱": "寵聚股份有限公司/-",
        "成立時間": "2015",
        "統一編號": "24964969",
        "公司狀態": "核准設立",
        "團隊人數": "未揭露",
        "實收資本額(元/新台幣)": "9,112,460",
        "負責人": "程科茗",
        "主分類": "CommunityandLifestyle",
        "官方網站": "https://www.pettalk.tw/",
        "專利狀況": "公告專利總數︰0；發明專利︰0；新型專利︰0；設計專利︰0",
        "產品/服務簡介": "寵物社群行銷-PetTalk說寵物",
        "公司簡介": "PetTalk是一個聚焦以寵物健康為出發點的公司,我們希望以現在互聯網的思維去幫助寵物產業升級,並以數據應用回饋給飼主與品牌商,幫助飼主得到需要的訊息,幫助品牌開發出更好的產品與銷售.我們的願景是以台灣為出發點,結合本身與合作夥伴的資源,快速打造新模式並進軍國際.此外〝寵物〞，是我們全部與唯一的事業。PetTalk的經營內容，完全服務于寵物市場，並整合行業經營與創新的平台操作，透過微型經濟消費體來聚集成一個宏觀的寵物圈經濟體，以實現寵物文化、品牌文化與企業文化三者的融合，並在飼主心目中形成長期的特殊偏好，成為PetTalk的競爭優勢。",
        "公司註冊地址": "臺北市中正區仁愛路2段25號5樓"
    }
]