[
    {
        "公司名稱": "瘋帽客科技股份有限公司/madhattertechnologyCo.,Ltd.",
        "成立時間": "2015",
        "統一編號": "29186700",
        "公司狀態": "核准設立",
        "團隊人數": "10",
        "實收資本額(元/新台幣)": "5,000,000",
        "負責人": "李庭昀",
        "主分類": "InformationTechnology",
        "官方網站": "http://www.madhattertw.com/",
        "專利狀況": "公告專利總數︰0；發明專利︰0；新型專利︰0；設計專利︰0",
        "產品/服務簡介": "軟硬體系統開發、Android/IOSAPP開發",
        "公司簡介": "經由嚴謹的需求訪談、專案控管、系統開發專案流程，我們致力於開發出符合人性效率化的系統平台。不論是專案控管、程式撰寫、會計業務，我們團隊都有效率地進行專業分工，讓每一個小螺絲丁都能發揮出最大的效能！我們使用MicrosoftAzure雲計算服務，量身打造出適合貴公司的雲端主機架構，不論是IOT、DataMining、資源控管通通難不倒它！",
        "公司註冊地址": "高雄市前鎮區復興四路12號10樓之6"
    }
]