[
    {
        "公司名稱": "綠芽能源科技有限公司/GreenBudTechnologyInc.",
        "成立時間": "2016",
        "統一編號": "55891478",
        "公司狀態": "核准設立",
        "團隊人數": "未揭露",
        "實收資本額(元/新台幣)": "0",
        "負責人": "陳家逵",
        "主分類": "Energy",
        "官方網站": "https://www.facebook.com/people/%E7%B6%A0%E8%8A%BD%E8%83%BD%E6%BA%90%E7%A7%91%E6%8A%80%E6%9C%89%E9%99%90%E5%85%AC%E5%8F%B8-55891478/100063628887212/",
        "專利狀況": "公告專利總數︰0；發明專利︰0；新型專利︰0；設計專利︰0",
        "產品/服務簡介": "-",
        "公司簡介": "主要是太陽能相關儲能、鋰電池、鋰鐵電池組裝訂製，銷售方向為電動車、電動自行車、機車、汽車、太陽能儲能、停電備用電池、電動工具電池新作維修訂製等。",
        "公司註冊地址": "屏東縣屏東市金泉里民族路1號1樓"
    }
]