[
    {
        "公司名稱": "海音數位創意有限公司/-",
        "成立時間": "2018",
        "統一編號": "50751574",
        "公司狀態": "核准設立",
        "團隊人數": "未揭露",
        "實收資本額(元/新台幣)": "0",
        "負責人": "廖家慧",
        "主分類": "Software",
        "官方網站": "https://factory.hiinmusic.com/",
        "專利狀況": "公告專利總數︰0；發明專利︰0；新型專利︰0；設計專利︰0",
        "產品/服務簡介": "專為企業設計及開發網頁/系統/應用",
        "公司簡介": "自從2013年起，『海音數位創意有限公司』的前身公司『海音網路股份有限公司』成立，由創辦人Doris帶領團隊開發了HiiNMUISC海浪音樂網，前前後後創立了Ppartner夥伴網、ToYouPOST明信片手機殼文創電商、來福網、HiiNpay單頁網路商店平台、HiiNTogo個人外帶簡易POS系統等自有平台產品。我們除了幫客戶打造專屬網站系統同時也是一間不折不扣的網路新創，將過去網路經營的經驗結合，更能為客戶規劃及設計最佳的設計方案。",
        "公司註冊地址": "臺北市內湖區陽光街345巷12號4樓"
    }
]