[
    {
        "公司名稱": "雲普科技股份有限公司/YOUPOSSYSTEMSINC.",
        "成立時間": "2012",
        "統一編號": "53778275",
        "公司狀態": "核准設立",
        "團隊人數": "未揭露",
        "實收資本額(元/新台幣)": "28,500,000",
        "負責人": "趙蔚新",
        "主分類": "CommerceandShopping",
        "官方網站": "http://wavesoft.com/tw/",
        "專利狀況": "公告專利總數︰0；發明專利︰0；新型專利︰0；設計專利︰0",
        "產品/服務簡介": "WaveSoft適用於iOS的餐廳管理系統，包含iKDS廚房訂單準備解決方案；WavePOS銷售點系統整合；WaveTOUCH行動應用解決方案。",
        "公司簡介": "WaveSoft是一家領先業界的軟件開發商，為私人、公共和企業客戶提供創新的通信技術系統，在餐飲業擁有特殊的專業知識。二十多年來，WaveSoft為數以千計的各種規模的食品和飲料企業提供服務——從快餐店、酒吧到高級餐廳。隨著行動裝置的普及和使用的增加，越來越多的企業正在尋找更新的技術來改善其餐廳業務。WaveSoft提供實現利潤和效率最大化所需的行動POS系統。我們的行動應用程式使用戶能夠執行線上訂單輸入、雲端數據處理以及支付應用程序，這些應用程序與幾乎任何第三方POS系統無縫整合。",
        "公司註冊地址": "臺北市內湖區瑞光路513巷39號4樓"
    }
]