[
    {
        "公司名稱": "吉晟生技股份有限公司/PETPHARMBIOTECHCO.,LTD.",
        "成立時間": "2011",
        "統一編號": "53541504",
        "公司狀態": "核准設立",
        "團隊人數": "未揭露",
        "實收資本額(元/新台幣)": "405,294,000",
        "負責人": "楊朝堂",
        "主分類": "Biotechnology",
        "官方網站": "http://www.petpharmbio.com/contact.html",
        "專利狀況": "公告專利總數︰0；發明專利︰0；新型專利︰0；設計專利︰0",
        "產品/服務簡介": "分子影像醫學用藥",
        "公司簡介": "專注於分子影像醫學用藥，建立全亞洲首座PIC/SGMP放射性無菌製劑廠，以提供全台醫院合法GMP藥廠生產的PET藥品；並致力於引進國際先進藥品，以及與國外研究機構合作研發針對新世紀各重大疾病藥物，以利台灣核醫藥品界與國際無縫接軌，提供國人一流且完善的核子醫療檢測與治療。",
        "公司註冊地址": "新北市新莊區後港一路141號1樓至2樓;143號1樓至2樓"
    }
]