[
    {
        "公司名稱": "堆疊股份有限公司/Bigstackco.,ltd",
        "成立時間": "2018",
        "統一編號": "50769842",
        "公司狀態": "核准設立",
        "團隊人數": "20",
        "實收資本額(元/新台幣)": "37,000,000",
        "負責人": "吳明勳",
        "主分類": "InternetServices",
        "官方網站": "https://www.bigstack.co",
        "專利狀況": "公告專利總數︰0；發明專利︰0；新型專利︰0；設計專利︰0",
        "產品/服務簡介": "BigstackCubeCloudHCI、Cube超融合雲平臺",
        "公司簡介": "Bigstack是一家專注於開源雲原生技術、多雲管理、軟體定義資料中心，和網路安全的軟體公司。透過CubeHCI超融合雲平台幫助企業擬定多雲策略從而實現IT自助服務、按需付費、自動化管理和服務持續整合發佈，並對基礎架構進行了全面的管理、維護和技術支援，讓所有企業可以自建複雜的雲環境，不需要龐大的IT團隊，以標準伺服器就能輕鬆打造如AWS、GCP、AZure等技術領先的雲計算平台。",
        "公司註冊地址": "臺北市中山區樂群三路130號6樓"
    }
]