[
    {
        "公司名稱": "來一碗餐飲有限公司/-",
        "成立時間": "2021",
        "統一編號": "90592552",
        "公司狀態": "核准設立",
        "團隊人數": "6",
        "實收資本額(元/新台幣)": "0",
        "負責人": "廖翊成",
        "主分類": "FoodandBeverage",
        "官方網站": "https://www.eateasy.com.tw/",
        "專利狀況": "公告專利總數︰0；發明專利︰0；新型專利︰0；設計專利︰0",
        "產品/服務簡介": "『來一碗』大腸麵線",
        "公司簡介": "『來一碗』當初單純的想法，簡單、好記、唸起來順口。於是，店名就這樣誕生了。SINE2003來一碗。大腸麵線在2003年於精明一街商圈經營大腸麵線、臭豆腐販售，20年間累積不少忠實顧客，也是台中知名小吃店之一。2021年成立來一碗餐飲有限公司，因想法跟做法與長輩不同，目前來一碗餐飲有限公司主要由二代經營，在口味上與創始店一致。",
        "公司註冊地址": "臺中市北區健行路572號1樓"
    }
]