[
    {
        "公司名稱": "恩可語股份有限公司/-",
        "成立時間": "2015",
        "統一編號": "24736348",
        "公司狀態": "解散",
        "團隊人數": "9",
        "實收資本額(元/新台幣)": "29,980,000",
        "負責人": "-",
        "主分類": "InformationTechnology",
        "官方網站": "Not Provided",
        "專利狀況": "公告專利總數︰2；發明專利︰1；新型專利︰1；設計專利︰0",
        "產品/服務簡介": "BiACE智慧空調節電系統。不是用電「管理監測」，恩可語一站到位幫企業節電節費！$0設備投資，15%以上節電保證，30天免費驗證，4小時快速安裝。客戶省下電費，支付月費，為恩可語創造累進式收入，接通其他能管平台，使節電確實落地，可複製擴張到海外。POC試點：遠傳、研華、CharoencableTV。",
        "公司簡介": "恩可語鎖定耗電量非常龐大的商業空調用電，創新研發出「BiACE智慧空調節電系統」，採取「免費安裝、30天免費驗證、有節電才收費」的創新商業服務模式，快速贏得國內許多商業用戶的青睞，更成功打進國際智慧節能市場，贏得全球智慧節能商機。BiACE服務推出短短一年，就獲得市場廣泛青睞，目前已經在國內140個商業空間，提供BiACE服務。謝豪哲說，在育成中心的推薦之下，恩可語成為2017年新北市企業節電888專案的執行單位之一，在新北市試營運階段，執行達成率100%，共嘉惠140家次客戶，對於新北市的節電成效貢獻卓著，也為恩可語後續推廣市場，帶來很大的幫助。另外，BiACE服務也在經濟部中小企業處的「107年第二次新創採購」中，獲得「智慧環保」項目評鑑第一名，正式進入政府的共同供應契約，上架政府電子採購網，更廣泛打開恩可語的全國市場；在企業用戶方面，目前國內包括璞石麗緻、富信飯店、瓏山林飯店、優美飯店在內的數十家飯店，都陸續導入BiACE服務。謝豪哲說，綜合各大用戶的使用回饋資料，BiACE平均約可為企業節省15%以上的電費。面向國際市場，恩可語也跟著南向腳步，成功打開泰國市場。林良澤說，在臺科大育成中心的媒合之下，BiACE服務已成功導入到泰國曼谷大型賣場，建立第一個海外實績，預估未來會以更快的速度打開泰國市場，甚至將市場開拓到整個東南亞，為恩可語往後的成長，創造龐大的潛在機會。",
        "公司註冊地址": "臺北市中正區羅斯福路3段100之93號"
    }
]