[
    {
        "公司名稱": "咖米股份有限公司/CareMeInc.",
        "成立時間": "2021",
        "統一編號": "90451321",
        "公司狀態": "核准設立",
        "團隊人數": "5",
        "實收資本額(元/新台幣)": "1,053,388",
        "負責人": "邱暘軒",
        "主分類": "HealthCare",
        "官方網站": "https://kameelife.com",
        "專利狀況": "公告專利總數︰1；發明專利︰0；新型專利︰1；設計專利︰0",
        "產品/服務簡介": "隨著疫情爆發以及現代人的生活型態，全球保健食品飛速成長，然而卻也浮現出一般民眾不知如何選擇適合自己的保健品、傳統瓶罐與通路購買的不方便性等問題。咖米提供1:1客製化保健食品訂閱服務，透過3分鐘使用咖米線上健康評估問卷系統，消費者就能得到最適合自己的保健食品推薦清單，並透過訂閱的方式，咖米將每月寄送一盒\"咖米盒子\"，內容30份每日包，一天一包就能補充一日所需營養素，讓您的健康補充更簡單、更方便、更客製！",
        "公司簡介": "咖米成立於2021年，是由一群台北醫學院畢業的醫療人士及工程師們組成的公司，因為咖米相信醫療產業的最終型態就是個人化，因此立志於透過數據驅動的解決方案，協助消費者針對個人狀況打造專屬的健康內容，包含保健食品、飲食、運動、生活型態等。也因此咖米參與了Google2022ProjectHatcher孵創計畫、SparkLabsTaiwan，希望透過個多產業結合，由科技解決人類的健康問題。",
        "公司註冊地址": "臺北市中正區忠孝西路1段102號12樓"
    }
]