[
    {
        "公司名稱": "信輝健康科技有限公司/XinHuiHealthTechnologyCorporationLtd.",
        "成立時間": "2019",
        "統一編號": "82911174",
        "公司狀態": "核准設立",
        "團隊人數": "未揭露",
        "實收資本額(元/新台幣)": "0",
        "負責人": "王信懿",
        "主分類": "HealthCare",
        "官方網站": "https://tcn.mypenguinsmart.com/",
        "專利狀況": "公告專利總數︰0；發明專利︰0；新型專利︰0；設計專利︰0",
        "產品/服務簡介": "打造父母成為居家早療教練；日常中即可有系統的引導孩子突破溝通發育障礙，數位科技讓父母有早療主控權；短期內看到孩子溝通發展的成效",
        "公司簡介": "PenguinSmart發起于美國矽谷，由麻省理工與哈佛校友聯合創辦，推動智慧型客製化復健支持服務，為病患家屬賦能，成為家人復健過程的重要參與者。現從影響全球1/6孩子的溝通力發育問題開始，圍繞家長關注的“我孩子目前發育進度是否正常？”和“若有發育落後的問題，我現在可以怎麼做？”等問題，線上服務關注孩子發育的海內外華人家庭。其客製化資料平臺不僅有效實現“以家庭為核心”的早期療育模式，更8倍延展每一專業治療師的服務範圍與人群。至今，已與多家醫療與教育單位協作，共同服務廣大海內外華人家庭。由美國顛覆者日報評選為全球育兒類十大顛覆型企業，及入圍2021年“世界前百大醫療遠見獎”。近期更獲得全美第一之企業新創加速器AlchemistAccelerator及國際加速器SparkLabs背書，追求“為每個家庭釋出最大健康幸福潛力”的願景。",
        "公司註冊地址": "臺北市大同區民生西路236號2樓"
    }
]