[
    {
        "公司名稱": "霖揚生技製藥股份有限公司/GenoviorBiotechCorporation",
        "成立時間": "2015",
        "統一編號": "24890496",
        "公司狀態": "核准設立",
        "團隊人數": "165",
        "實收資本額(元/新台幣)": "1,226,810,000",
        "負責人": "徐展平",
        "主分類": "Biotechnology",
        "官方網站": "https://tw.genovior.com.tw/",
        "專利狀況": "公告專利總數︰0；發明專利︰0；新型專利︰0；設計專利︰0",
        "產品/服務簡介": "霖揚生技為專業CDMO/CMO(委託開發、委託製造)藥廠,旨在提供國內外客戶優質、便利及有效的全方位服務,滿足客戶從臨床到商業化的需要。",
        "公司簡介": "霖揚生技於民國104年4月23日成立，擁有優秀的團隊，由徐展平博士主持，並邀請國內外專家共襄盛舉，專精於研發、製造、法規服務，為國際化的/專業一條龍的CDMO/CMO(委託開發、委託製造)藥廠，積極朝全球國際化佈局發展，培養國際化人才，使營業規模及觸角持續穩定擴大，追求企業永續經營成長。隨著大量專利到期的蛋白質藥物和大分子新藥導入市場，大分子藥物已成為21世紀的主流，產能需求遽增。霖揚生技看準此商機，透過技術移轉、客戶仲介與客戶共同開發等模式，接受全球知名生技製藥公司的委託製造胜肽、蛋白質、單株抗體等原料藥和預置型/長效型針劑，並提供藥物傳輸系統新技術開發等垂直整合之服務。",
        "公司註冊地址": "苗栗縣竹南鎮科研路50-8號4樓"
    }
]