[
    {
        "公司名稱": "櫻桃服務股份有限公司/CHERRYPAYPTE.LTD.",
        "成立時間": "2016",
        "統一編號": "52243083",
        "公司狀態": "解散",
        "團隊人數": "未揭露",
        "實收資本額(元/新台幣)": "3,000,000",
        "負責人": "-",
        "主分類": "FinancialServices",
        "官方網站": "Not Provided",
        "專利狀況": "公告專利總數︰0；發明專利︰0；新型專利︰0；設計專利︰0",
        "產品/服務簡介": "跨境支付、匯兌的媒合平台",
        "公司簡介": "CherryPay是採P2P模式的跨境支付、匯兌的媒合平台。團隊的成員，都對跨境購物抱持著無比的熱情或長年旅居海外，於頻繁的匯款過程中，發現傳統跨境轉帳嚴重的不便利性。CherryPay企圖打造別於傳統，最省錢、最聰明、最省時的國際轉帳代付渠道！經過長期的測試與實驗，只要輕鬆幾個步驟，兩個不同地方的人們可通過CherryPay找到另外一地的用戶，協助彼此快速將款項提轉帳給海外的家人、朋友以及日常生活開銷！",
        "公司註冊地址": "臺北市大安區信義路3段106號10樓之4"
    }
]