[
    {
        "公司名稱": "華西亞生醫股份有限公司/VAXSIABIOMEDICALINC.",
        "成立時間": "2010",
        "統一編號": "29171100",
        "公司狀態": "核准設立",
        "團隊人數": "2",
        "實收資本額(元/新台幣)": "15,750,000",
        "負責人": "甘銘中",
        "主分類": "Biotechnology",
        "官方網站": "http://www.vaxsia.com/",
        "專利狀況": "公告專利總數︰1；發明專利︰1；新型專利︰0；設計專利︰0",
        "產品/服務簡介": "VADEX疫苗載體技術",
        "公司簡介": "華西亞生醫股份有限公司（VaxsiaBiomedicalInc.）公司網址：www.vaxsia.com華西亞生醫創立於2010年7月。2013年11月通過申請成為南港生技育成中心第一類會員。華西亞生醫是一個研發型的新創生技公司，專長領域是疫苗抗原運輸及奈米粒子技術。公司自行開發的VADEX技術可將抗原聚合成奈米粒子並主動吸附免疫佐劑，同時達到提高抗體效價及安全性的目的。",
        "公司註冊地址": "臺北市南港區園區街3號17樓"
    }
]