[
    {
        "公司名稱": "閎崎有限公司/KARINECO.,LTD.",
        "成立時間": "2013",
        "統一編號": "54283883",
        "公司狀態": "核准設立",
        "團隊人數": "未揭露",
        "實收資本額(元/新台幣)": "0",
        "負責人": "林建凱",
        "主分類": "ConsumerGoods",
        "官方網站": "http://www.karine.com.tw/v2/official",
        "專利狀況": "公告專利總數︰0；發明專利︰0；新型專利︰0；設計專利︰0",
        "產品/服務簡介": "手工鞋",
        "公司簡介": "Karine中文音譯為卡瑞妮，在地MIT手工製鞋；設計好搭舒適，定位優質平價。國內老師傅的堅持與專業展現，在高成本與細膩工法一決勝負。",
        "公司註冊地址": "宜蘭縣五結鄉協和村五結路二段266巷12弄13號一樓"
    }
]