[
    {
        "公司名稱": "迪英佳科技股份有限公司/HERE-APPSCO.,LTD.",
        "成立時間": "2013",
        "統一編號": "28113624",
        "公司狀態": "核准設立",
        "團隊人數": "7",
        "實收資本額(元/新台幣)": "3,833,340",
        "負責人": "羅棨鐘",
        "主分類": "InternetServices",
        "官方網站": "Not Provided",
        "專利狀況": "公告專利總數︰2；發明專利︰1；新型專利︰1；設計專利︰0",
        "產品/服務簡介": "物聯網雲端平台",
        "公司簡介": "迪英佳科技股份有限公司秉持著對生活保持樂觀、幽默與積極的態度，HERE團隊不斷嘗試於生活中、科技中尋找各種解決方案，提升生活品質與便利性，並不忘時時創新及對社會保有高度服務熱忱。本公司原以室內定位技術與應用起家，其後經歷市場調適與策略軸轉，目前專注於物聯網與穿戴式裝置研發，提供藍牙低功耗(BLE)與Zigbee技術之消費性智慧應用服務。同時，HERE團隊亦發揮創新研發設計與垂直整合服務之能力，致力於建立一簡單且低成本之物聯網軟硬整合雲端平台，可做為開發者與製造商之間的溝通橋樑，加速物聯網產業的活絡性，為使用者提供最完善的整合性服務；藉由此軟硬整合方案，企業僅需專注於自身所專長業務，透過迪英佳的技術支援，為企業發揮其最大之營運效益。",
        "公司註冊地址": "新竹市北區康樂里東大路三段305-9號一樓"
    }
]