[
    {
        "公司名稱": "富萊特國際股份有限公司/FreightaceInternationalCo.,LTD",
        "成立時間": "2012",
        "統一編號": "53836063",
        "公司狀態": "核准設立",
        "團隊人數": "15",
        "實收資本額(元/新台幣)": "66,750,000",
        "負責人": "周子騫",
        "主分類": "Transportation",
        "官方網站": "https://www.iletscargo.com/Views/Home/#/Air",
        "專利狀況": "公告專利總數︰0；發明專利︰0；新型專利︰0；設計專利︰0",
        "產品/服務簡介": "以電商貨為主的海、空運和倉儲服務，以及針對物流行業研發的AI物流服務",
        "公司簡介": "富萊特國際自2015年成立以來，透過自行研發的系統，已整合了許多我們的物流夥伴，在傳統的物流供應鏈從陸、海、空(運)到倉儲、與進出口清關及報驗，從流程效率強化到人力配置最佳化，注入新創的精神，以專業的經驗與最新的技術提供給客戶令人驚豔的體驗。",
        "公司註冊地址": "臺北市大安區光復南路102號5樓"
    }
]