[
    {
        "公司名稱": "智禾金碳股份有限公司/-",
        "成立時間": "2022",
        "統一編號": "90395790",
        "公司狀態": "核准設立",
        "團隊人數": "未揭露",
        "實收資本額(元/新台幣)": "246,500,000",
        "負責人": "陳坤宏",
        "主分類": "Energy",
        "官方網站": "https://www.greenharvest.com.tw/tw/about",
        "專利狀況": "公告專利總數︰0；發明專利︰0；新型專利︰0；設計專利︰0",
        "產品/服務簡介": "規劃運營沙崙智慧能源管理系統",
        "公司簡介": "宏碁與太陽能暨能源管理廠商睿禾控股共同宣布，取得「沙崙智慧綠能科學城智慧能源管理系統BOT案」，合作成立特許公司「智禾金碳股份有限公司」共同打造全國第一個智慧綠能示範園區。建置太陽光電發電設備、儲能設備、智慧電網及能源管理中心，推動創能、儲能、節能及智慧系統整合之能源轉型，打造沙崙科學城虛擬電廠，進行電力調度與負載管理。",
        "公司註冊地址": "臺南市歸仁區高發二路360號"
    }
]