[
    {
        "公司名稱": "鈞昊有限公司/DR.ACMECO.,LTD",
        "成立時間": "2012",
        "統一編號": "53840524",
        "公司狀態": "核准設立",
        "團隊人數": "未揭露",
        "實收資本額(元/新台幣)": "0",
        "負責人": "吳銘鈞",
        "主分類": "ConsumerGoods",
        "官方網站": "Not Provided",
        "專利狀況": "公告專利總數︰0；發明專利︰0；新型專利︰0；設計專利︰0",
        "產品/服務簡介": "面膜肌活乳",
        "公司簡介": "L’MASQUEEN創辦人-Adriano於多年前在歐洲生活時發現，當地不少的在地品牌僅以簡單的植物萃取成分以及傳統配方便可調配出溫和天然的肌膚產品，於是回台灣後率領研發團隊，採用零污染有機天然植物萃取為原料，依循專業醫師的指導和建議，在多次嘗試之下，成立符合東方人膚質，溫和低刺激的保養品牌L’MASQUEEN。",
        "公司註冊地址": "高雄市鼓山區鼓山二路166巷68號2樓"
    }
]