[
    {
        "公司名稱": "台灣前瞻電漿股份有限公司/-",
        "成立時間": "2021",
        "統一編號": "90838562",
        "公司狀態": "核准設立",
        "團隊人數": "1",
        "實收資本額(元/新台幣)": "2,000,000",
        "負責人": "李慧芳",
        "主分類": "Hardware",
        "官方網站": "Not Provided",
        "專利狀況": "公告專利總數︰0；發明專利︰0；新型專利︰0；設計專利︰0",
        "產品/服務簡介": "滅菌箱產品",
        "公司簡介": "台灣前瞻電漿成立於民國110年2月，為師生創業團隊，與本校吳宗信老師所領導的「氣熱電漿物理實驗室」進行合作，目前正致力朝向將電漿科技及微細氣泡結合應用，並以低溫常壓電漿為核心技術，發展民生、醫療等應用領域產品為目標。",
        "公司註冊地址": "臺南市東區成大里育樂街66巷8號6樓"
    }
]