[
    {
        "公司名稱": "尼爾互動股份有限公司/-",
        "成立時間": "2022",
        "統一編號": "90207517",
        "公司狀態": "核准設立",
        "團隊人數": "8",
        "實收資本額(元/新台幣)": "6,500,000",
        "負責人": "李振安",
        "主分類": "MediaandEntertainment",
        "官方網站": "Not Provided",
        "專利狀況": "公告專利總數︰0；發明專利︰0；新型專利︰0；設計專利︰0",
        "產品/服務簡介": "直播軟體開發產品與娛樂互動",
        "公司簡介": "關於沙盒互動，是一家專注於「互動」的軟體開發公司，公司核心成員來自遊戲娛樂開發、系統整合等領域，主要業務為直播軟體開發產品與娛樂互動相關項目，建立以開放的架構來鼓勵更多的開發者投入創建直播應用軟體市場，開發具競爭力的直播產品，其期能為更多不同銷售領域的直播主提供更為適切的資訊服務",
        "公司註冊地址": "新北市林口區仁愛路2段502號9樓"
    }
]