[
    {
        "公司名稱": "翔探科技股份有限公司/AEROPROBINGINC.",
        "成立時間": "2015",
        "統一編號": "24977373",
        "公司狀態": "核准設立",
        "團隊人數": "未揭露",
        "實收資本額(元/新台幣)": "43,070,170",
        "負責人": "陳麗茵",
        "主分類": "Hardware",
        "官方網站": "https://aeroprobing.com/en/",
        "專利狀況": "公告專利總數︰0；發明專利︰0；新型專利︰0；設計專利︰0",
        "產品/服務簡介": "無人機電控系統設計開發、無人機地面站軟體設計開發、無人機自動化應用系統整合設計、精準農業無人機產品供應",
        "公司簡介": "翔探科技股份有限公司(AeroprobingInc.)成立於2015年，為台灣頂尖專業無人機技術開發商之一，更是專精於無人機應用解決方案開發的台灣航太設備製造商。創立初衷專注於無人機飛航控制、自動導航及管理系統技術的開發，並打下深厚的無人機應用科技基礎。除了自有系統軟硬體整合技術，亦是人工智能結合無人機航控系統的技術領導者。翔探科技無人機科技客戶涵蓋政府機關、國際企業用戶及各級研究單位；應用技術領域包含建築檢測與測繪、無人機農業應用科技與物流技術開發等，而在無人機巡檢的應用上，搭配自有的導控軟體更能將檢測的程序自動化，一方面可以提升檢測效率，縮短檢測時間以減少人力的依賴度。未來將輔以AI人工智慧辨識技術，更能實現即時辨識，不依賴後製人眼辨識的高效巡檢功能。目前翔探科技團隊以無人機控制領域的研究為基礎，推出各種工業用無人機整機客制化方案，並提供各種相關之多軸旋翼無人機飛控系統參考設計及顧問諮詢服務準備為下個世代的電腦視覺智能無人機設計推出最佳的設計參考以及商品整合方案。",
        "公司註冊地址": "新北市新店區寶興路87巷1號3樓"
    }
]