[
    {
        "公司名稱": "大千智慧股份有限公司/94BOTCO.,LTD.",
        "成立時間": "2017",
        "統一編號": "52602947",
        "公司狀態": "核准設立",
        "團隊人數": "未揭露",
        "實收資本額(元/新台幣)": "20,833,320",
        "負責人": "侯一郎",
        "主分類": "Software",
        "官方網站": "http://94bot.com/",
        "專利狀況": "公告專利總數︰0；發明專利︰0；新型專利︰0；設計專利︰0",
        "產品/服務簡介": "94bot智慧機器人。全通道對話管理、歡迎訊息設定、全方位對話歷程掌控、快又準的網頁對話輸入提示、簡單有效的知識庫優化。",
        "公司簡介": "創造全方位、人機合一的智慧客服體驗，升級顧客服務體驗的最佳解決方案。",
        "公司註冊地址": "臺北市松山區八德路4段28號2樓之1"
    }
]