[
    {
        "公司名稱": "狄卡科技股份有限公司/DCARDTAIWANLTD.",
        "成立時間": "2015",
        "統一編號": "42656367",
        "公司狀態": "核准設立",
        "團隊人數": "45",
        "實收資本額(元/新台幣)": "150,000,000",
        "負責人": "林裕欽",
        "主分類": "CommunityandLifestyle",
        "官方網站": "https://www.dcard.tw/",
        "專利狀況": "公告專利總數︰0；發明專利︰0；新型專利︰0；設計專利︰0",
        "產品/服務簡介": "提供社群網路服務",
        "公司簡介": "Dcard提供有別於具名的Facebook、匿名的PTT，是一個匿名卻又經實名認證過的社群論壇，只揭露發文者的有限資訊，減少匿名暴力，也讓大家可以保有隱私沒有壓力地交流，滿足大家想要一個沒有現實身份拘束的交流、分享空間，並有更流暢的使用者體驗上，滿足台灣年輕人想要一個屬於這個世代的公眾交流平台需求。",
        "公司註冊地址": "臺北市大安區光復南路102號11樓"
    }
]