[
    {
        "公司名稱": "默科資訊股份有限公司/MERCUEINFORMATIONCO.,LTD.",
        "成立時間": "2012",
        "統一編號": "54027890",
        "公司狀態": "核准設立",
        "團隊人數": "未揭露",
        "實收資本額(元/新台幣)": "3,000,000",
        "負責人": "洪克昌",
        "主分類": "InformationTechnology",
        "官方網站": "Not Provided",
        "專利狀況": "公告專利總數︰1；發明專利︰1；新型專利︰0；設計專利︰0",
        "產品/服務簡介": "SHOWCUE",
        "公司簡介": "Showcue展場聲波定位服務，展場利用超音波廣播設備，建立室位定位功能，民眾可用手機事先讀取廠商資料並標示廠商於室內的位置，方便進入展場後迅速找到有興趣的攤位，並可藉由感應蒐集廠商電子名片或產品eDM，雙方也能直接透過app聯繫。默科資訊主要發展音波技術，利用音波來進行資料傳遞/鍊結，與國內外廠商合作，以提供一般民眾更加舒適/便利的生活環境，期望成為立足台灣，放眼全球的一流公司。",
        "公司註冊地址": "新北市板橋區雙十路2段10之1號8樓"
    }
]