[
    {
        "公司名稱": "宇川精密材料科技股份有限公司/PENTAPROMATERIALSINC.",
        "成立時間": "2011",
        "統一編號": "53322851",
        "公司狀態": "核准設立",
        "團隊人數": "未揭露",
        "實收資本額(元/新台幣)": "500,000,000",
        "負責人": "郭文哲",
        "主分類": "Manufacturing",
        "官方網站": "http://www.ppmiglobal.com/",
        "專利狀況": "公告專利總數︰5；發明專利︰3；新型專利︰2；設計專利︰0",
        "產品/服務簡介": "金屬有機產品",
        "公司簡介": "宇川精密材料科技股份有限公司成立於民國一百年，是台灣首創有機金屬專業製造服務的公司。身為專業有機金屬製造服務公司，宇川公司在提供先進的有機金屬產品與服務已建立聲譽。自創立開始，宇川公司即持續提供客戶最先進的產品與服務。宇川公司藉由與每個客戶所建立的堅強的夥伴關係，穩定地創造了強而有力的成長。全球的有機金屬客戶因信任宇川公司的產品與服務，使用宇川公司的有機金屬產品，廣泛地運用在LED、半導體、太陽能等多樣應用領域。",
        "公司註冊地址": "新竹縣竹北市文興路一段358號2樓"
    }
]