[
    {
        "公司名稱": "安富財經科技股份有限公司/ANFUSOLUTIONSCO.,LTD.",
        "成立時間": "2015",
        "統一編號": "42757837",
        "公司狀態": "核准設立",
        "團隊人數": "5",
        "實收資本額(元/新台幣)": "5,000,000",
        "負責人": "楊太樂",
        "主分類": "FinancialServices",
        "官方網站": "https://www.anfusolutions.com/",
        "專利狀況": "公告專利總數︰3；發明專利︰0；新型專利︰3；設計專利︰0",
        "產品/服務簡介": "1.好時價(HOUSE+)不動產自動估價平台https://www.houseplus.tw/2.模型開發與驗證3.投資組合和資產管理4.證券化設計和執行5.壓力測試和監管諮詢6.客製化軟體與APP7.合作平台開發",
        "公司簡介": "在安富，我們喜歡做我們擅長的工作。我們專精於量化分析、抵押金融、政策評估和財務管理，我們的總公司在美國華盛頓特區，過去15年中一直為美國政府、半官方企業、私營部門和其他地區的金融機構提供服務。我們的使命是提供金融工程、風險管理和融資方案設計的整體規畫與實踐，以提升客戶的工作效率和強化競爭力為目標。我們不斷創新量化技能並與豐富的經驗相結合，我們能夠創造滿足客戶需求的解決方案。而誠信是我們最重視的原則，我們在時間和預算內履行我們的承諾。",
        "公司註冊地址": "桃園市中壢區忠福里南園二路381巷5弄6號1樓"
    }
]