[
    {
        "公司名稱": "墨策國際股份有限公司/JIMMYS.P.A.PLUSCO.,LTD.",
        "成立時間": "2014",
        "統一編號": "24753232",
        "公司狀態": "核准設立",
        "團隊人數": "未揭露",
        "實收資本額(元/新台幣)": "22,000,000",
        "負責人": "李雨珊",
        "主分類": "SalesandMarketing",
        "官方網站": "https://www.jimmyspa.com/tw",
        "專利狀況": "公告專利總數︰0；發明專利︰0；新型專利︰0；設計專利︰0",
        "產品/服務簡介": "讓幾米的繪本故事和精神哲學以各種形式轉譯呈現",
        "公司簡介": "以幾米繪本為原點出發的幾米品牌，自2000年起透過墨色國際開展品牌經營，讓幾米的繪本故事和精神哲學以各種形式轉譯呈現，在影視改編、周邊商品、展演裝置等領域都有亮眼成績，是華人文創產業中一源多用與跨域整合的重要案例。在幾米品牌創立15週年之際，墨色國際成立墨策國際，恪守並延續幾米品牌原有的核心價值，將專職各類跨界合作專案、影視、文化展演與品牌拓展之策略規劃，在未來更加強化幾米作品內容的轉換和運用，致力於幾米品牌的國際市場推廣和產值創造。",
        "公司註冊地址": "新北市林口區文化三路1段555巷11號2樓"
    }
]