[
    {
        "公司名稱": "必應創造股份有限公司/B'INLIVECO.,LTD.",
        "成立時間": "2014",
        "統一編號": "54663862",
        "公司狀態": "核准設立",
        "團隊人數": "未揭露",
        "實收資本額(元/新台幣)": "489,724,880",
        "負責人": "周佑洋",
        "主分類": "MediaandEntertainment",
        "官方網站": "http://www.bin-live.com/",
        "專利狀況": "公告專利總數︰2；發明專利︰1；新型專利︰1；設計專利︰0",
        "產品/服務簡介": "節目內容發想、企劃與執行、視覺及舞台設計、燈光、音響規劃及租賃、工程統籌",
        "公司簡介": "必應創造團隊統合累積近十年來的經驗值大成，承接超過千場以上的演出活動，以近兩年為例，每年參與200場以上演唱會或頒獎典禮等現場工作，平均每2天全世界就有一場由必應創造成員參與的演唱會正在進行中，不但獲得各唱片公司及廠商的讚賞，也得到演出藝人的信賴與好評，更為華語樂壇創造許多經典的巡迴演唱會，如「五月天–DNA世界巡迴演唱會」、「五月天–諾亞方舟世界巡迴演唱會」、「李宗盛–既然青春留不住巡迴演唱會」、「林宥嘉–神遊巡迴演唱會」、「S.H.E.–TogetherForever世界巡迴演唱會」等，並創下將台灣原創製作的演唱會推向北京鳥巢，締造10萬人場地演出的輝煌紀錄。",
        "公司註冊地址": "臺北市內湖區新湖一路370號3樓"
    }
]