[
    {
        "公司名稱": "蟲小道大股份有限公司/WormaxInc.",
        "成立時間": "2019",
        "統一編號": "54990211",
        "公司狀態": "核准設立",
        "團隊人數": "未揭露",
        "實收資本額(元/新台幣)": "21,900,000",
        "負責人": "許承軒",
        "主分類": "AgricultureandFarming",
        "官方網站": "https://www.wormaxinc.com/",
        "專利狀況": "公告專利總數︰0；發明專利︰0；新型專利︰0；設計專利︰0",
        "產品/服務簡介": "「黑水虻」蟲原蛋白",
        "公司簡介": "蟲小道大主要以「黑水虻」製作新型動物性蛋白，並提供畜產飼料優質蛋白新型來源。我們公司遵循著歐盟及美國AAFCO的表準程序進行養殖。將來自天然的農業副產物(酒糟、豆渣及咖啡渣等)植物性的原料進行餌料配置與飼養，在飼養過程中，絕不使用任何廚餘及糞便作為餌料來源，以達到國外昆蟲飼養之標準。",
        "公司註冊地址": "彰化縣二水鄉文化村民族路88號1樓"
    }
]