[
    {
        "公司名稱": "揚大生技股份有限公司/YANGDABIOTECHCO.,LTD.",
        "成立時間": "2010",
        "統一編號": "53285384",
        "公司狀態": "解散",
        "團隊人數": "未揭露",
        "實收資本額(元/新台幣)": "5,000,000",
        "負責人": "-",
        "主分類": "FoodandBeverage",
        "官方網站": "http://www.yangda.com.tw/",
        "專利狀況": "公告專利總數︰0；發明專利︰0；新型專利︰0；設計專利︰0",
        "產品/服務簡介": "-",
        "公司簡介": "為了將福釀坊系列更多元化，堅持使用台灣農產，用心嚴選台灣道地的農產品，如台東金峰鄉的洛神花、台東壢坵村的咖啡、台南梅嶺的胭脂梅、台北三峽的抹茶，再加上研究單一菌種微生物經過完整糖化、酒化、醋化的發酵過程所精釀而成，完整的將天然材料的營養素萃取保存，提升醋的品質。福釀坊品牌核心價值在於遵循傳統釀造法運用創新技術將發酵產品延伸出無限可能，且嚴選台灣農業素材，以減少碳足跡珍愛大地，堅持採用產地當季食材新鮮製作，希望帶給大家健康。",
        "公司註冊地址": "屏東縣長治鄉德和村神農路1號"
    }
]