[
    {
        "公司名稱": "聯齊科技股份有限公司/NextDriveCo.",
        "成立時間": "2013",
        "統一編號": "54310122",
        "公司狀態": "核准設立",
        "團隊人數": "10",
        "實收資本額(元/新台幣)": "75,000,000",
        "負責人": "顏哲淵",
        "主分類": "Energy",
        "官方網站": "https://www.nextdrive.io/",
        "專利狀況": "公告專利總數︰3；發明專利︰2；新型專利︰1；設計專利︰0",
        "產品/服務簡介": "能源物聯網平台",
        "公司簡介": "NextDrive的能源物聯網平台提供從能源閘道器、雲端運算、到裝置數據管理平台的完整服務架構；解決方案包括HEMS家庭能源管理、CEMS場域型能源管理系統和API資料串接介面，為電力公司、能源業者、企業客戶和終端消費者帶來全方位的新能源應用方案",
        "公司註冊地址": "臺北市南港區昆陽街18號2樓"
    }
]