[
    {
        "公司名稱": "熊快樂開發企業有限公司/HAPPYBEARDEVELOPMENTENTERPRISECO.,LTD.",
        "成立時間": "2013",
        "統一編號": "54212585",
        "公司狀態": "核准設立",
        "團隊人數": "20",
        "實收資本額(元/新台幣)": "0",
        "負責人": "曾文衍",
        "主分類": "TravelandTourism",
        "官方網站": "http://www.bearforest.com.tw/",
        "專利狀況": "公告專利總數︰0；發明專利︰0；新型專利︰0；設計專利︰0",
        "產品/服務簡介": "客房住宿、餐飲服務、旅遊諮詢、周邊商品、民宿代管",
        "公司簡介": "【有熊的森林villa】座落於花蓮壽豐鄉雲山水園區，已於2014年第三季完工。本著對花蓮這塊土地的熱情，致力於將花蓮的美好傳遞給熱愛這份土地的所有朋友們，選在花蓮雲山水落地生根，作為夢想種子的孕育地。我們將提供一流的設備、管家專屬服務、精選的在地食材、各式各樣的體驗活動以及不定期的舉行藝文展覽等等，希望能讓前來的貴賓，留下難忘的回憶。",
        "公司註冊地址": "高雄市前鎮區復興四路2號10樓之1"
    }
]