[
    {
        "公司名稱": "英屬開曼群島商睿勝科技股份有限公司/-",
        "成立時間": "2015",
        "統一編號": "24804252",
        "公司狀態": "核准登記",
        "團隊人數": "未揭露",
        "實收資本額(元/新台幣)": "0",
        "負責人": "李冠緯",
        "主分類": "Software",
        "官方網站": "https://www.retair.com/#/retchat-home",
        "專利狀況": "公告專利總數︰0；發明專利︰0；新型專利︰0；設計專利︰0",
        "產品/服務簡介": "消費者與品牌互動平台熱茶雲=消費者數據權益X品牌顧客經營X企業數據賦能",
        "公司簡介": "我們是一家雲端客戶體驗與數據管理軟體公司(SaaS)我們是基於BigDatatechnology(SparkStreaming/Cassandra/Kafka/Greenplum)的SaaS服務商，專注於雲端大數據探勘及推薦系統的研發與運營服務！我們CEO/CTO均是在美國矽谷有多年創業/出場經驗，A輪由日本知名創投領投，客戶面向全世界合作夥伴包含廣告、醫療、金融、政府與新零售等領域。我們是以人工智慧技術為核心的服務商，提供：◆使客戶節約了資金成本透過海量資料分析，使傳統企業、商家等團隊能快速擁抱移動互聯網帶來的商機，更專注自身的核心競爭力◆節約了大量的人力成本和時間透過強大的推薦系統，使客戶自家的產品能夠在市場上快速推出與成長！透過自身演算法整合線上線下零碎零售數據，拼湊完整顧客面貌，再推播客製化促銷折扣訊息提高銷售額",
        "公司註冊地址": "臺北市中正區同安街93號2樓之1"
    }
]