[
    {
        "公司名稱": "群健科技股份有限公司/CofitHealthcareInc.",
        "成立時間": "2014",
        "統一編號": "24770801",
        "公司狀態": "核准設立",
        "團隊人數": "10",
        "實收資本額(元/新台幣)": "30,934,920",
        "負責人": "陳陽光",
        "主分類": "HealthCare",
        "官方網站": "https://events.cofit.me/",
        "專利狀況": "公告專利總數︰0；發明專利︰0；新型專利︰0；設計專利︰0",
        "產品/服務簡介": "健康管理App、專家管理軟體、線上飲食課程、健康食譜/社群/商城經營、診所行銷和經營管理",
        "公司簡介": "Cofit是一間數位醫療領域的公司，致力於結合醫療專業和科技，幫助人們改變習慣、吃得更健康，進而改善肥胖和飲食相關慢性病問題。主要產品是線上營養服務、健康管理App以及營養師和教練使用的健康管理系統。已經有上千位來自台灣、香港和大陸各地的付費用戶，以及數萬名想減重、雕塑或吃更健康的使用者註冊。進而結合穿戴裝置、醫療設備，和健康餐外送、餐廳等，整合互聯網工具和營養專業，提供給健身房、醫療院所和企業整合性的專業資源，一起打造完整的健康管理服務及高互動社群。",
        "公司註冊地址": "臺北市中山區松江路363號12樓"
    }
]