[
    {
        "公司名稱": "延電智能有限公司/YenprotekAIoTLTD",
        "成立時間": "2022",
        "統一編號": "90344028",
        "公司狀態": "核准設立",
        "團隊人數": "未揭露",
        "實收資本額(元/新台幣)": "0",
        "負責人": "張鶴騰",
        "主分類": "InternetServices",
        "官方網站": "https://www.yenprotek.com/",
        "專利狀況": "公告專利總數︰0；發明專利︰0；新型專利︰0；設計專利︰0",
        "產品/服務簡介": "AIoT環境感測設備與環境監控系統、各類型統計系統、警報警示系統",
        "公司簡介": "延電智能專注於AIoT設備開發，結合AI、IoT及5G技術，幫助使用者以更少的人力與成本監控環境以及遠端控制設備。",
        "公司註冊地址": "桃園市楊梅區高鐵南路十段599巷88弄3號"
    }
]