[
    {
        "公司名稱": "天原資管股份有限公司/ORIGININFORMATIONCORPORATION",
        "成立時間": "2014",
        "統一編號": "24756391",
        "公司狀態": "核准設立",
        "團隊人數": "未揭露",
        "實收資本額(元/新台幣)": "12,000,000",
        "負責人": "黃端祥",
        "主分類": "InformationTechnology",
        "官方網站": "Not Provided",
        "專利狀況": "公告專利總數︰0；發明專利︰0；新型專利︰0；設計專利︰0",
        "產品/服務簡介": ".net應用系統開發與維運",
        "公司簡介": "目前最主要的業務著重於.net的應用系統開發與舊有的資訊系統維運。主要的客戶群是政府機構及民間企業，各50%左右。除原有市場耕耘，近期也著力於個人音樂雲相關的解決方案。",
        "公司註冊地址": "臺北市中正區忠孝東路1段35號10樓"
    }
]