[
    {
        "公司名稱": "東鈺科技有限公司/-",
        "成立時間": "2018",
        "統一編號": "42724061",
        "公司狀態": "核准設立",
        "團隊人數": "未揭露",
        "實收資本額(元/新台幣)": "0",
        "負責人": "劉國興",
        "主分類": "Sustainability",
        "官方網站": "Not Provided",
        "專利狀況": "公告專利總數︰0；發明專利︰0；新型專利︰0；設計專利︰0",
        "產品/服務簡介": "環保、資源回收、資源回收設備規劃與設計",
        "公司簡介": "因為東京奧運做了相當良好的智慧環境教育資源回收再利用的示範，連金牌、銀牌、銅牌、選手睡的床等等都是資源回收再利用的成果，這對於本公司說服通路有相當大的幫助，目前從事智慧環保科技,資源回收科技藝術教育,研發創新等.",
        "公司註冊地址": "新北市板橋區國慶路182巷1號5樓之1"
    }
]