[
    {
        "公司名稱": "優護平台股份有限公司/Ucarerlnc.",
        "成立時間": "2015",
        "統一編號": "42654776",
        "公司狀態": "核准設立",
        "團隊人數": "未揭露",
        "實收資本額(元/新台幣)": "60,000,000",
        "負責人": "陳宏益",
        "主分類": "HealthCare",
        "官方網站": "https://ucarer.tw/",
        "專利狀況": "公告專利總數︰0；發明專利︰0；新型專利︰0；設計專利︰0",
        "產品/服務簡介": "優照護是一家第三方預約照護平台，提供即時、資訊透明、專業的照護媒合服務。我們的主要產品包括提供照護人員、物理/職能治療師、藝術輔療師、營養師等專業人員的預約照護服務，以及各種針對企業的B2B解決方案。此外，我們還為高齡者提供最完善的「精準照護」服務，讓他們能夠在家中享受到優質照護。透過我們的平台，不僅能夠方便地尋找到安全又合適的護理師、護士、照顧服務員等，同時也讓照護人員能自主管理個案，安全地提供服務，並且增加收入來源。我們的目標是讓台灣照護市場的資訊更加流通，創造優質照護環境。",
        "公司簡介": "優護平台「優照護」成立於台灣，因瞭解三明治世代的照護壓力，運用居家照護、互聯網技術和平台營運三大優勢，成為台灣第一家高齡照護媒合平台。除了提供高齡者相關媒合服務資訊，優照護還增加了全方位企業「B2B高齡照顧解決方案」。目前擁有累積超過90,000會員家庭、2,000位照護夥伴和300位專業人士，並與超過百家企業合作。創辦人陳宏益先生超前部屬，於2015年成立全臺第一家高齡照護「媒合」平台，為應對2025年超高齡社會的來臨而做好準備。透過創新的電子商務結合照護服務，優照護獲得了第15屆國家新創獎、連續三年經濟部中小企業處社創良品、經濟部中小企業處「公益科技創新應用」提案競賽優勝等多項國家級殊榮。在「優照護」團隊中，多元學習並整合跨域資源是現在世界趨勢，且這種趨勢也在團隊中得到了實踐。透過學習多元銷售模式的電子商務，創新平台經濟，以及接軌世界潮流SDGs/ESG永續發展理念，團隊成員可以不斷提升自我價值，推廣永續議題並建立更多社會福祉三贏新契機。",
        "公司註冊地址": "臺北市大安區羅斯福路3段149號8樓之1"
    }
]